am_lama/__init__.py
am_lama/addons/__init__.py
am_lama/addons/autots/base.py
am_lama/addons/hypex/README.md
am_lama/addons/hypex/__init__.py
am_lama/addons/hypex/algorithms/faiss_matcher.py
am_lama/addons/hypex/matcher.py
am_lama/addons/hypex/selectors/lama_feature_selector.py
am_lama/addons/hypex/selectors/outliers_filter.py
am_lama/addons/hypex/selectors/spearman_filter.py
am_lama/addons/hypex/utils/metrics.py
am_lama/addons/hypex/utils/psi_pandas.py
am_lama/addons/hypex/utils/validators.py
am_lama/addons/interpretation/__init__.py
am_lama/addons/interpretation/data_process.py
am_lama/addons/interpretation/l2x.py
am_lama/addons/interpretation/l2x_model.py
am_lama/addons/interpretation/lime.py
am_lama/addons/interpretation/utils.py
am_lama/addons/tabular_interpretation/__init__.py
am_lama/addons/tabular_interpretation/sswarm.py
am_lama/addons/uplift/__init__.py
am_lama/addons/uplift/base.py
am_lama/addons/uplift/metalearners.py
am_lama/addons/uplift/metrics.py
am_lama/addons/uplift/utils.py
am_lama/addons/utilization/__init__.py
am_lama/addons/utilization/utilization.py
am_lama/automl/__init__.py
am_lama/automl/base.py
am_lama/automl/blend.py
am_lama/automl/presets/__init__.py
am_lama/automl/presets/base.py
am_lama/automl/presets/image_config.yml
am_lama/automl/presets/image_presets.py
am_lama/automl/presets/tabular_config.yml
am_lama/automl/presets/tabular_configs/conf_0_sel_type_0.yml
am_lama/automl/presets/tabular_configs/conf_1_sel_type_1.yml
am_lama/automl/presets/tabular_configs/conf_2_select_mode_1_no_typ.yml
am_lama/automl/presets/tabular_configs/conf_3_sel_type_1_no_inter_lgbm.yml
am_lama/automl/presets/tabular_configs/conf_4_sel_type_0_no_int.yml
am_lama/automl/presets/tabular_configs/conf_5_sel_type_1_tuning_full.yml
am_lama/automl/presets/tabular_configs/conf_6_sel_type_1_tuning_full_no_int_lgbm.yml
am_lama/automl/presets/tabular_presets.py
am_lama/automl/presets/text_config.yml
am_lama/automl/presets/text_presets.py
am_lama-0.3.8.2.dist-info/METADATA
am_lama-0.3.8.2.dist-info/WHEEL
am_lama-0.3.8.2.dist-info/licenses/LICENSE
am_lama-0.3.8.2.dist-info/RECORD
